MANIFEST.in
README.rst
setup.py
src/digimat/__init__.py
src/digimat.datalogger.egg-info/PKG-INFO
src/digimat.datalogger.egg-info/SOURCES.txt
src/digimat.datalogger.egg-info/dependency_links.txt
src/digimat.datalogger.egg-info/namespace_packages.txt
src/digimat.datalogger.egg-info/not-zip-safe
src/digimat.datalogger.egg-info/requires.txt
src/digimat.datalogger.egg-info/top_level.txt
src/digimat/datalogger/__init__.py
src/digimat/datalogger/__main__.py
src/digimat/datalogger/datalogger.py
src/digimat/datalogger/ftp.py
src/digimat/datalogger/ftpdcf.py