Metadata-Version: 1.0
Name: digimat.datalogger
Version: 0.0.1
Summary: Digimat Simple DataLogger
Home-page: http://www.digimat.ch
Author: Frederic Hess
Author-email: fhess@st-sa.ch
License: PSF
Platform: UNKNOWN
